CHANGES.rst
LICENSE.txt
README.rst
_fsevents.c
compat.c
compat.h
fsevents.py
setup.py
MacFSEvents.egg-info/PKG-INFO
MacFSEvents.egg-info/SOURCES.txt
MacFSEvents.egg-info/dependency_links.txt
MacFSEvents.egg-info/not-zip-safe
MacFSEvents.egg-info/top_level.txt