Metadata-Version: 2.1
Name: MacFSEvents
Version: 0.8.4
Summary: Thread-based interface to file system observation primitives.
Home-page: https://github.com/malthe/macfsevents
Author: Malthe Borch
Author-email: mborch@gmail.com
License: BSD
Platform: Mac OS X
Classifier: Development Status :: 4 - Beta
Classifier: Intended Audience :: Developers
Classifier: License :: OSI Approved :: BSD License
Classifier: Operating System :: MacOS :: MacOS X
Classifier: Programming Language :: C
Classifier: Programming Language :: Python :: 2.4
Classifier: Programming Language :: Python :: 2.5
Classifier: Programming Language :: Python :: 2.6
Classifier: Programming Language :: Python :: 2.7
Classifier: Programming Language :: Python :: 3.7
Classifier: Programming Language :: Python :: 3.8
Classifier: Programming Language :: Python :: 3.9
Classifier: Programming Language :: Python :: 3.10
Classifier: Topic :: Software Development :: Libraries :: Python Modules
Classifier: Topic :: System :: Filesystems
License-File: LICENSE.txt
